Workbook

Sheet Portafolio_Base
A1: Ticker | B1: DIR_COTIZACION | C1: Nombre | D1: Mercado | E1: Tipo | F1: Moneda | G1: TRM | H1: Cantidad | I1: Precio Promedio Compra | J1: Precio Mercado Actual | K1: Inversión Inicial (Moneda Origen) | L1: Valor Mercado Actual (Moneda Origen) | M1: Ganancia No Realizada (Moneda Origen) | N1: Inversión Inicial (COP) | O1: Valor Mercado Actual (COP) | P1: Ganancia No Realizada (COP) | Q1: Rendimiento Porcentual | R1: Dividendos Recibidos (COP) | S1: Variación Día (%)
A2: NVDACO | B2: NVDACO.CL | C2: NVIDIA Corporation | D2: MGC | E2: Accion | F2: COP | G2: 1 | H2: 1 | I2: 422640 | J2: 735020 | K2: =H2*I2 | L2: =H2*J2 | M2: =L2-K2 | N2: =IF(F2="COP", K2, K2*G2) | O2: =IF(F2="COP", L2, L2*G2) | P2: =O2-N2 | Q2: =IFERROR(P2/N2, 0) | R2: 781.15 | S2: 0
A3: MINEROS | B3: MINEROS.CL | C3: Mineros S.A. | D3: BVC | E3: Accion | F3: COP | G3: 1 | H3: 2 | I3: 18200 | J3: 22860 | K3: =H3*I3 | L3: =H3*J3 | M3: =L3-K3 | N3: =IF(F3="COP", K3, K3*G3) | O3: =IF(F3="COP", L3, L3*G3) | P3: =O3-N3 | Q3: =IFERROR(P3/N3, 0) | R3: 339.1 | S3: 0
A4: LTMCO | B4: LTMCO.CL | C4: Latam Airlines | D4: MGC | E4: Accion | F4: COP | G4: 1 | H4: 294 | I4: 59.5 | J4: 85 | K4: =H4*I4 | L4: =H4*J4 | M4: =L4-K4 | N4: =IF(F4="COP", K4, K4*G4) | O4: =IF(F4="COP", L4, L4*G4) | P4: =O4-N4 | Q4: =IFERROR(P4/N4, 0) | R4: 884.78 | S4: 0
A5: IUITCO | B5: IUITCO.CL | C5: iShares S&P 500 Tech | D5: MGC | E5: ETF | F5: COP | G5: 1 | H5: 4 | I5: 85965 | J5: 183440 | K5: =H5*I5 | L5: =H5*J5 | M5: =L5-K5 | N5: =IF(F5="COP", K5, K5*G5) | O5: =IF(F5="COP", L5, L5*G5) | P5: =O5-N5 | Q5: =IFERROR(P5/N5, 0) | R5: 0 | S5: 0
A6: ISA | B6: ISA.CL | C6: Interconexion Electrica SA | D6: BVC | E6: Accion | F6: COP | G6: 1 | H6: 7 | I6: 22802.5 | J6: 30020 | K6: =H6*I6 | L6: =H6*J6 | M6: =L6-K6 | N6: =IF(F6="COP", K6, K6*G6) | O6: =IF(F6="COP", L6, L6*G6) | P6: =O6-N6 | Q6: =IFERROR(P6/N6, 0) | R6: 11163 | S6: 0
A7: ICOLCAP | B7: ICOLCAP.CL | C7: iShares Colcap ETF | D7: BVC | E7: ETF | F7: COP | G7: 1 | H7: 12 | I7: 11916.37 | J7: 25846 | K7: =H7*I7 | L7: =H7*J7 | M7: =L7-K7 | N7: =IF(F7="COP", K7, K7*G7) | O7: =IF(F7="COP", L7, L7*G7) | P7: =O7-N7 | Q7: =IFERROR(P7/N7, 0) | R7: 48030.52 | S7: 0
A8: ICHNCO | B8: ICHNCO.CL | C8: iShares MSCI China UCITS | D8: MGC | E8: ETF | F8: COP | G8: 1 | H8: 6 | I8: 22600 | J8: 18344 | K8: =H8*I8 | L8: =H8*J8 | M8: =L8-K8 | N8: =IF(F8="COP", K8, K8*G8) | O8: =IF(F8="COP", L8, L8*G8) | P8: =O8-N8 | Q8: =IFERROR(P8/N8, 0) | R8: 0 | S8: 0
A9: GEB | B9: GEB.CL | C9: Grupo Energia Bogota | D9: BVC | E9: Accion | F9: COP | G9: 1 | H9: 40 | I9: 2836.25 | J9: 3080 | K9: =H9*I9 | L9: =H9*J9 | M9: =L9-K9 | N9: =IF(F9="COP", K9, K9*G9) | O9: =IF(F9="COP", L9, L9*G9) | P9: =O9-N9 | Q9: =IFERROR(P9/N9, 0) | R9: 8397.91 | S9: 0
A10: ETB | B10: ETB.CL | C10: Empresa Telecomunicaciones Bogota | D10: BVC | E10: Accion | F10: COP | G10: 1 | H10: 317 | I10: 45 | J10: 135 | K10: =H10*I10 | L10: =H10*J10 | M10: =L10-K10 | N10: =IF(F10="COP", K10, K10*G10) | O10: =IF(F10="COP", L10, L10*G10) | P10: =O10-N10 | Q10: =IFERROR(P10/N10, 0) | R10: 0 | S10: 0
A11: ENELAMCO | B11: ENELAMCO.CL | C11: Enel Americas SA | D11: MGC | E11: Accion | F11: COP | G11: 1 | H11: 100 | I11: 401 | J11: 295 | K11: =H11*I11 | L11: =H11*J11 | M11: =L11-K11 | N11: =IF(F11="COP", K11, K11*G11) | O11: =IF(F11="COP", L11, L11*G11) | P11: =O11-N11 | Q11: =IFERROR(P11/N11, 0) | R11: 1719.29 | S11: 0
A12: ECOPETROL | B12: ECOPETROL.CL | C12: Ecopetrol S.A. | D12: BVC | E12: Accion | F12: COP | G12: 1 | H12: 86 | I12: 1995.25 | J12: 2740 | K12: =H12*I12 | L12: =H12*J12 | M12: =L12-K12 | N12: =IF(F12="COP", K12, K12*G12) | O12: =IF(F12="COP", L12, L12*G12) | P12: =O12-N12 | Q12: =IFERROR(P12/N12, 0) | R12: 38468.99 | S12: 0
A13: CIBEST | B13: CIBEST.CL | C13: Bancolombia | D13: BVC | E13: Accion | F13: COP | G13: 1 | H13: 2 | I13: 35100 | J13: 89600 | K13: =H13*I13 | L13: =H13*J13 | M13: =L13-K13 | N13: =IF(F13="COP", K13, K13*G13) | O13: =IF(F13="COP", L13, L13*G13) | P13: =O13-N13 | Q13: =IFERROR(P13/N13, 0) | R13: 6164 | S13: 0
A14: AMDVASCO | B14: AMDVASCCO.CL | C14: DVA Silicon Fund | D14: MGC | E14: Fondo/Accion | F14: COP | G14: 1 | H14: 6 | I14: 14300 | J14: 34220 | K14: =H14*I14 | L14: =H14*J14 | M14: =L14-K14 | N14: =IF(F14="COP", K14, K14*G14) | O14: =IF(F14="COP", L14, L14*G14) | P14: =O14-N14 | Q14: =IFERROR(P14/N14, 0) | R14: 765.6 | S14: 0
A15: NU | B15: NU | C15: Nu Holdings Ltd. | D15: USD | E15: Accion | F15: USD | G15: =IFERROR(GOOGLEFINANCE("CURRENCY:USDCOP"), 4150) | H15: 2 | I15: 12.45 | J15: 12.44 | K15: =H15*I15 | L15: =H15*J15 | M15: =L15-K15 | N15: =IF(F15="COP", K15, K15*G15) | O15: =IF(F15="COP", L15, L15*G15) | P15: =O15-N15 | Q15: =IFERROR(P15/N15, 0) | R15: 0 | S15: 0
A16: ACON | B16: ACON | C16: Aclarion, Inc. | D16: USD | E16: Accion | F16: USD | G16: =IFERROR(GOOGLEFINANCE("CURRENCY:USDCOP"), 4150) | H16: 2 | I16: 2.59 | J16: 2.39 | K16: =H16*I16 | L16: =H16*J16 | M16: =L16-K16 | N16: =IF(F16="COP", K16, K16*G16) | O16: =IF(F16="COP", L16, L16*G16) | P16: =O16-N16 | Q16: =IFERROR(P16/N16, 0) | R16: 0 | S16: 0
A17: Total | N17: =SUM(N2:N16) | O17: =SUM(O2:O16) | P17: =SUM(P2:P16) | Q17: =IFERROR(P17/N17, 0) | R17: =SUM(R2:R16) | S17: =IFERROR(SUMPRODUCT(O2:O16, S2:S16)/SUM(O2:O16), 0)

Sheet Resumen_Global
A1: MÉTRICA / CONCEPTO | B1: VALOR CONSOLIDADO (COP) | C1: DETALLE TÉCNICO
A2: Valor Mercado Acciones y ETFs | B2: =Portafolio_Base!O17 | C2: Total valorizado en COP (BVC + MGC + USA)
A3: Inversión Inicial Total | B3: =Portafolio_Base!N17 | C3: Costo base consolidado en pesos colombianos
A4: Ganancia No Realizada Total | B4: =Portafolio_Base!P17 | C4: Plusvalía neta acumulada
A5: Rendimiento Ponderado Global | B5: =Portafolio_Base!Q17 | C5: Retorno porcentual de la cartera
A6: Total Dividendos Recibidos | B6: =Portafolio_Base!R17 | C6: Flujo histórico de dividendos cobrados
A7: Fondos Trii (FICs) | B7: 26364.08 | C7: Fondos colectivos de inversión en Trii
A8: Saldo Disponible en Efectivo | B8: 14457.28 | C8: Liquidez sin invertir en la cuenta
A9: PATRIMONIO TOTAL EN TRII | B9: =B2+B7+B8 | C9: Patrimonio neto consolidado (Acciones + Fondos + Saldo)

Sheet Historico_Snapshots
A1: Fecha y Hora | B1: Inversión Inicial (COP) | C1: Valor Mercado Acciones/ETFs (COP) | D1: Fondos Trii (COP) | E1: Saldo Efectivo (COP) | F1: Patrimonio Total (COP) | G1: Rendimiento %
A2: 2026-09-30 08:30:00 | B2: 1754013.4 | C2: 2985477 | D2: 26364.08 | E2: 14457.28 | F2: 3026298.4 | G2: 0.7021

Sheet Historico_Precios_Activos
A1: Fecha y Hora | B1: Ticker | C1: Nombre | D1: Mercado | E1: Precio Actual (COP) | F1: Cierre Previo (COP) | G1: Variación Día (COP) | H1: Variación Día (%) | I1: Volumen
A2: 2026-09-30 08:30:00 | B2: ECOPETROL | C2: Ecopetrol S.A. | D2: BVC | E2: 2740 | F2: 2740 | G2: 0 | H2: 0 | I2: 154200
